{
	"configurations" : 
	[
		{
			"directories" : 
			[
				{
					"build" : ".",
					"jsonFile" : "directory-.-Debug-f5ebdc15457944623624.json",
					"minimumCMakeVersion" : 
					{
						"string" : "3.28"
					},
					"projectIndex" : 0,
					"source" : ".",
					"targetIndexes" : 
					[
						0
					]
				}
			],
			"name" : "Debug",
			"projects" : 
			[
				{
					"directoryIndexes" : 
					[
						0
					],
					"name" : "TextX",
					"targetIndexes" : 
					[
						0
					]
				}
			],
			"targets" : 
			[
				{
					"directoryIndex" : 0,
					"id" : "TextX::@6890427a1f51a3e7e1df",
					"jsonFile" : "target-TextX-Debug-c8be30bf5ebfad77d42b.json",
					"name" : "TextX",
					"projectIndex" : 0
				}
			]
		}
	],
	"kind" : "codemodel",
	"paths" : 
	{
		"build" : "/Users/puneetsharma/Projects/TextX/cmake-build-debug",
		"source" : "/Users/puneetsharma/Projects/TextX"
	},
	"version" : 
	{
		"major" : 2,
		"minor" : 6
	}
}
